[
  {
    "judul": "Pemudik Se-Indonesia Mulai Padati Stasiun Bekasi Jelang Libur Akhir Tahun",
    "deskripsi": "Kedatangan penumpang meningkat hingga 45% dibandingkan pekan lalu.",
    "gambar": "stasiun.png",
    "link": "https://update1.com"
  },
  {
    "judul": "Pemerintah Siapkan Bantuan untuk Warga Terdampak Banjir",
    "deskripsi": "Bantuan berupa makanan siap saji dan obat-obatan mulai disalurkan.",
    "gambar": "banjir.png",
    "link": "https://update2.com"
  },
  {
    "judul": "Jalan Raya Babelan Akan Diperbaiki Awal Tahun 2026",
    "deskripsi": "Proyek peningkatan jalan dilakukan untuk mengurai kemacetan.",
    "gambar": "perbaikan-jalan.png",
    "link": "https://update3.com"
  },
  {
    "judul": "Startup Bekasi Kembangkan Aplikasi Jual Beli Sembako",
    "deskripsi": "Aplikasi ini memungkinkan warga berbelanja sembako dari rumah.",
    "gambar": "sembako.png",
    "link": "https://update4.com"
  },
  {
    "judul": "Layanan Internet Gratis Diluncurkan di 38 Sekolah",
    "deskripsi": "Program ini ditargetkan selesai di seluruh sekolah tahun depan.",
    "gambar": "wifi.png",
    "link": "https://update5.com"
  },
  {
    "judul": "Turnamen Mobile Legends Antar Pelajar Digelar di Bekasi",
    "deskripsi": "Total hadiah mencapai Rp 30 juta untuk para pemenang.",
    "gambar": "mlbb.png",
    "link": "https://update6.com"
  },
  {
    "judul": "Minimarket 24 Jam Bertambah di Daerah Perumahan",
    "deskripsi": "Menjawab kebutuhan warga akan layanan belanja nonstop.",
    "gambar": "minimarket.png",
    "link": "https://update7.com"
  },
  {
    "judul": "Kebakaran Gudang Plastik Berhasil Dipadamkan",
    "deskripsi": "Kebakaran terjadi pukul 02.45 dan tidak ada korban jiwa.",
    "gambar": "kebakaran.png",
    "link": "https://update8.com"
  },
  {
    "judul": "Harga Ayam Potong Mengalami Penurunan",
    "deskripsi": "Harga turun sekitar Rp 4.000 per kilogram di pasaran.",
    "gambar": "ayam.png",
    "link": "https://update9.com"
  },
  {
    "judul": "Bus Bekasi — Blok M Tambah 25 Armada Baru",
    "deskripsi": "Jadwal keberangkatan menjadi lebih sering tanpa jeda panjang.",
    "gambar": "bus.png",
    "link": "https://update10.com"
  },
  {
    "judul": "Penggunaan QRIS di Pasar Tradisional Meningkat Tajam",
    "deskripsi": "Transaksi digital kini mencapai lebih dari 60%.",
    "gambar": "qris.png",
    "link": "https://update11.com"
  },
  {
    "judul": "Perpustakaan Digital Bekasi Diluncurkan",
    "deskripsi": "Lebih dari 12.000 buku dapat diakses warga secara online.",
    "gambar": "perpustakaan.png",
    "link": "https://update12.com"
  },
  {
    "judul": "Relawan Bersihkan Sampah Sungai Kaliabang",
    "deskripsi": "Kegiatan diikuti lebih dari 120 peserta dari berbagai komunitas.",
    "gambar": "sungai.png",
    "link": "https://update13.com"
  },
  {
    "judul": "Event Bekasi Culinary Night Sukses Menarik Ribuan Pengunjung",
    "deskripsi": "Kuliner khas Nusantara menjadi daya tarik terbesar.",
    "gambar": "kuliner.png",
    "link": "https://update14.com"
  },
  {
    "judul": "Sistem Pengaduan Online Untuk Warga Resmi Diperkenalkan",
    "deskripsi": "Pengaduan dapat langsung dipantau melalui aplikasi.",
    "gambar": "pengaduan.png",
    "link": "https://update15.com"
  },
  {
    "judul": "Program Vaksin Gratis Hewan Peliharaan Digelar",
    "deskripsi": "Pendaftaran sudah dibuka untuk 2.500 pemilik hewan.",
    "gambar": "vaksin-hewan.png",
    "link": "https://update16.com"
  },
  {
    "judul": "Lomba Foto Kota Bekasi Dibuka untuk Umum",
    "deskripsi": "Karya terbaik akan dipajang di alun-alun kota.",
    "gambar": "lomba-foto.png",
    "link": "https://update17.com"
  },
  {
    "judul": "Air Bersih Mulai Normal di Beberapa Wilayah",
    "deskripsi": "PDAM menyelesaikan perbaikan instalasi pompa dalam waktu dua hari.",
    "gambar": "air-bersih.png",
    "link": "https://update18.com"
  },
  {
    "judul": "Kenaikan Tarif Transportasi Online Ditunda",
    "deskripsi": "Kebijakan ditunda untuk menjaga daya beli masyarakat.",
    "gambar": "ojol.png",
    "link": "https://update19.com"
  },
  {
    "judul": "Film Lokal Tembus 8 Juta Penonton dalam 12 Hari",
    "deskripsi": "Film bergenre drama keluarga ini mendapat apresiasi tinggi dari masyarakat.",
    "gambar": "film.png",
    "link": "https://update20.com"
  }
]
